executorlib_core/__init__.py
executorlib_core/_version.py
executorlib_core/base.py
executorlib_core/communication.py
executorlib_core/inputcheck.py
executorlib_core/shell.py
executorlib_core/subprocess.py
executorlib_core/thread.py
executorlib_core-0.0.1.dist-info/LICENSE
executorlib_core-0.0.1.dist-info/METADATA
executorlib_core-0.0.1.dist-info/WHEEL
executorlib_core-0.0.1.dist-info/top_level.txt
executorlib_core-0.0.1.dist-info/RECORD
