Metadata-Version: 2.1
Name: executorlib-core
Version: 0.0.1
Summary: Library to develop your own concurrent.futures.Executor classes.
Author-email: Jan Janssen <janssen@mpie.de>
License: BSD 3-Clause License
Project-URL: Homepage, https://github.com/executorlib/executorlib-core
Project-URL: Documentation, https://executorlib-core.readthedocs.io
Project-URL: Repository, https://github.com/executorlib/executorlib-core
Keywords: pyiron
Classifier: Development Status :: 5 - Production/Stable
Classifier: Topic :: Scientific/Engineering :: Physics
Classifier: License :: OSI Approved :: BSD License
Classifier: Intended Audience :: Science/Research
Classifier: Operating System :: OS Independent
Classifier: Programming Language :: Python :: 3.9
Classifier: Programming Language :: Python :: 3.10
Classifier: Programming Language :: Python :: 3.11
Classifier: Programming Language :: Python :: 3.12
Requires-Python: <3.13,>=3.9
License-File: LICENSE
Requires-Dist: cloudpickle <=3.0.0,>=2.0.0
Requires-Dist: pyzmq <=26.0.2,>=25.0.0
Requires-Dist: tqdm <=4.66.2,>=4.44.0
